bank_transfer_qrcode/__init__.py
bank_transfer_qrcode/bank_transfer_qr.py
bank_transfer_qrcode/exceptions.py
bank_transfer_qrcode/field_definitions.py
bank_transfer_qrcode-0.1.0.dist-info/LICENSE
bank_transfer_qrcode-0.1.0.dist-info/METADATA
bank_transfer_qrcode-0.1.0.dist-info/WHEEL
bank_transfer_qrcode-0.1.0.dist-info/top_level.txt
bank_transfer_qrcode-0.1.0.dist-info/RECORD
