Metadata-Version: 2.1
Name: bank-transfer-qrcode
Version: 0.1.0
Summary: QR codes for bank transfers with banking applications
Author-email: Karol Podgórski <karolsoon.dev@gmail.com>
Maintainer-email: Karol Podgórski <karolsoon.dev@gmail.com>
License: Copyright (c) 2024, Karol Podgórski
Project-URL: Homepage, https://github.com/Karolsoon/Bank-Transfer-QR
Project-URL: Source, https://github.com/Karolsoon/Bank-Transfer-QR
Keywords: QR Code,qrcode,transfer,payment
Classifier: License :: OSI Approved :: BSD License
Classifier: Intended Audience :: Developers
Classifier: Programming Language :: Python
Classifier: Programming Language :: Python :: 3
Classifier: Topic :: Software Development :: Libraries :: Python Modules
Classifier: Topic :: Office/Business :: Financial
Classifier: Topic :: Utilities
Requires-Python: >=3.11
License-File: LICENSE
Requires-Dist: segno >=1.6.1
Provides-Extra: build
Requires-Dist: build ; extra == 'build'
Requires-Dist: twine ; extra == 'build'
Provides-Extra: dev
Requires-Dist: bumpver ; extra == 'dev'
Requires-Dist: pytest ; extra == 'dev'
